pyramid_bootstrap/__init__.py
pyramid_bootstrap/event_subscribers.py
pyramid_bootstrap/library.py
pyramid_bootstrap/spec.py
pyramid_bootstrap/static/bs4/font-awesome/css/font-awesome.css
pyramid_bootstrap/static/bs4/font-awesome/css/font-awesome.css.map
pyramid_bootstrap/static/bs4/font-awesome/css/font-awesome.min.css
pyramid_bootstrap/static/bs4/font-awesome/fonts/FontAwesome.otf
pyramid_bootstrap/static/bs4/font-awesome/fonts/fontawesome-webfont.eot
pyramid_bootstrap/static/bs4/font-awesome/fonts/fontawesome-webfont.svg
pyramid_bootstrap/static/bs4/font-awesome/fonts/fontawesome-webfont.ttf
pyramid_bootstrap/static/bs4/font-awesome/fonts/fontawesome-webfont.woff
pyramid_bootstrap/static/bs4/font-awesome/fonts/fontawesome-webfont.woff2
pyramid_bootstrap/static/bs4/jquery/jquery.js
pyramid_bootstrap/static/bs4/jquery/jquery.min.js
pyramid_bootstrap/static/bs4/jquery/jquery.min.map
pyramid_bootstrap/static/bs4/popper.js/umd/popper.js
pyramid_bootstrap/static/bs4/popper.js/umd/popper.min.js
pyramid_bootstrap/static/bs4/popper.js/umd/popper.min.js.map
pyramid_bootstrap/static/bs4/twitter-bootstrap/css/bootstrap.css
pyramid_bootstrap/static/bs4/twitter-bootstrap/css/bootstrap.css.map
pyramid_bootstrap/static/bs4/twitter-bootstrap/css/bootstrap.min.css
pyramid_bootstrap/static/bs4/twitter-bootstrap/css/bootstrap.min.css.map
pyramid_bootstrap/static/bs4/twitter-bootstrap/js/bootstrap.js
pyramid_bootstrap/static/bs4/twitter-bootstrap/js/bootstrap.js.map
pyramid_bootstrap/static/bs4/twitter-bootstrap/js/bootstrap.min.js
pyramid_bootstrap/static/bs4/twitter-bootstrap/js/bootstrap.min.js.map
pyramid_bootstrap/templates/bs4/google.jinja2
pyramid_bootstrap/templates/bs4/layout.jinja2
pyramid_bootstrap/templates/bs4/master.pt
pyramid_bootstrap/templates/bs4/pagination.jinja2
pyramid_bootstrap/templates/bs4/utils.jinja2
pyramid_bootstrap/templates/bs4/wtf.jinja2
pyramid_bootstrap4-4.1.0.dist-info/LICENSE.txt
pyramid_bootstrap4-4.1.0.dist-info/METADATA
pyramid_bootstrap4-4.1.0.dist-info/RECORD
pyramid_bootstrap4-4.1.0.dist-info/WHEEL
pyramid_bootstrap4-4.1.0.dist-info/top_level.txt
tests/__init__.py
tests/test_pyramid_bootstrap.py
