Metadata-Version: 2.1
Name: pyramid-bootstrap4
Version: 4.1.0
Summary: Bootstrap 4.0 for Pyramid
Home-page: https://github.com/joeblackwaslike/pyramid_bootstrap
Author: Joe Black
Author-email: me@joeblack.nyc
Maintainer: Joe Black
Maintainer-email: me@joeblack.nyc
License: MIT
Download-URL: https://github.com/joeblackwaslike/pyramid_bootstrap/tarball/v4.1.0
Keywords: pyramid,bootstrap,reponsive,framework
Platform: UNKNOWN
Classifier: Development Status :: 4 - Beta
Classifier: Intended Audience :: Developers
Classifier: License :: OSI Approved :: MIT License
Classifier: Operating System :: OS Independent
Classifier: Natural Language :: English
Classifier: Programming Language :: Python :: 3
Classifier: Programming Language :: Python :: 3.3
Classifier: Programming Language :: Python :: 3.4
Classifier: Programming Language :: Python :: 3.5
Classifier: Programming Language :: Python :: 3.6
Classifier: Programming Language :: Python :: 3 :: Only
Classifier: Topic :: Internet :: WWW/HTTP
Classifier: Topic :: Software Development
Classifier: Topic :: Software Development :: Libraries :: Python Modules
Requires-Dist: Pyramid (>=1.9.1)
